word_family_counter/__init__.py
word_family_counter/main.py
word_family_counter/measure_resources.py
word_family_counter-0.1.1.dist-info/METADATA
word_family_counter-0.1.1.dist-info/WHEEL
word_family_counter-0.1.1.dist-info/entry_points.txt
word_family_counter-0.1.1.dist-info/licenses/LICENSE
word_family_counter-0.1.1.dist-info/RECORD
