Metadata-Version: 2.3
Name: word_family_counter
Version: 0.1.1
Summary: A script for counting word families in a text file.
Project-URL: Homepage, https://github.com/BlueBirdBack/word_family_counter
Project-URL: Issues, https://github.com/BlueBirdBack/word_family_counter/issues
Project-URL: Documentation, https://github.com/BlueBirdBack/word_family_counter#readme
Project-URL: Repository, https://github.com/BlueBirdBack/word_family_counter.git
Author-email: BlueBirdBack <avery@bluebirdback.com>
License: MIT License
License-File: LICENSE
Keywords: linguistics,nlp,text analysis,word families
Classifier: Development Status :: 3 - Alpha
Classifier: Intended Audience :: Developers
Classifier: License :: OSI Approved :: MIT License
Classifier: Operating System :: OS Independent
Classifier: Programming Language :: Python :: 3
Classifier: Programming Language :: Python :: 3.8
Classifier: Programming Language :: Python :: 3.9
Classifier: Programming Language :: Python :: 3.10
Classifier: Programming Language :: Python :: 3.11
Classifier: Topic :: Text Processing :: Linguistic
Requires-Python: >=3.8
Requires-Dist: contractions<1.0.0,>=0.1.0
Requires-Dist: psutil<6.0.0,>=5.8.0
Requires-Dist: spacy<4.0.0,>=3.0.0
